httpie_http_message_signatures.py
httpie_http_message_signatures-0.0.2.dist-info/LICENSE
httpie_http_message_signatures-0.0.2.dist-info/METADATA
httpie_http_message_signatures-0.0.2.dist-info/WHEEL
httpie_http_message_signatures-0.0.2.dist-info/entry_points.txt
httpie_http_message_signatures-0.0.2.dist-info/RECORD
