Metadata-Version: 2.1
Name: httpie-http-message-signatures
Version: 0.0.2
Summary: HTTP Message Signatures plugin for HTTPie
Home-page: https://github.com/deceze/httpie-http-message-signatures
Keywords: httpie,http-signature,message-signatures
Author: David Zentgraf
Author-email: david@kunststube.net
Requires-Python: >=3.7
Classifier: Development Status :: 3 - Alpha
Classifier: Environment :: Plugins
Classifier: Intended Audience :: Developers
Classifier: License :: OSI Approved :: MIT License
Classifier: Programming Language :: Python :: 3
Classifier: Programming Language :: Python :: 3.7
Classifier: Programming Language :: Python :: 3.8
Classifier: Programming Language :: Python :: 3.9
Classifier: Programming Language :: Python :: 3.10
Classifier: Programming Language :: Python :: 3.11
Classifier: Programming Language :: Python :: 3
Classifier: Programming Language :: Python :: 3.7
Classifier: Topic :: Internet :: WWW/HTTP
Requires-Dist: http-message-signatures (>=0.4.4,<0.5.0)
Requires-Dist: httpie (>=3.2.2,<4.0.0)
Project-URL: Documentation, https://github.com/deceze/httpie-http-message-signatures
Project-URL: Repository, https://github.com/deceze/httpie-http-message-signatures
